zowe_secrets_for_zowe_sdk-1.0.0.dev12.dist-info/METADATA
zowe_secrets_for_zowe_sdk-1.0.0.dev12.dist-info/WHEEL
zowe/secrets_for_zowe_sdk/__init__.py
zowe/secrets_for_zowe_sdk/keyring.abi3.so
zowe_secrets_for_zowe_sdk-1.0.0.dev12.dist-info/RECORD
